[
  {
    "day": "Sunday (Prep Day)",
    "hour_by_hour": [
      {
        "time": "9:00 AM PST",
        "activity": "Final consciousness team briefing and preparation",
        "responsible": "Full Team",
        "notes": "Review consciousness messaging and coordination plan"
      },
      {
        "time": "12:00 PM PST",
        "activity": "Consciousness content pre-scheduling and automation setup",
        "responsible": "Marketing Team",
        "notes": "All consciousness social content ready for launch"
      },
      {
        "time": "3:00 PM PST",
        "activity": "Consciousness partner network final activation",
        "responsible": "Partner Team",
        "notes": "Confirm all consciousness advocates ready"
      },
      {
        "time": "6:00 PM PST",
        "activity": "Consciousness launch day content review and approval",
        "responsible": "Leadership",
        "notes": "Final consciousness messaging validation"
      }
    ],
    "key_milestones": [
      "Consciousness team fully briefed and prepared",
      "All consciousness content pre-scheduled and ready",
      "Partner consciousness network activated and confirmed",
      "Launch day consciousness plan final approval"
    ]
  },
  {
    "day": "Monday (T-1)",
    "hour_by_hour": [
      {
        "time": "12:01 AM PST",
        "activity": "Product Hunt consciousness submission goes live",
        "responsible": "Product Team",
        "notes": "Official consciousness platform launch on Product Hunt"
      },
      {
        "time": "6:00 AM PST",
        "activity": "Consciousness launch announcement across all channels",
        "responsible": "Marketing Team",
        "notes": "Coordinate consciousness messaging globally"
      },
      {
        "time": "9:00 AM PST",
        "activity": "Begin consciousness engagement and community activation",
        "responsible": "Full Team",
        "notes": "All hands consciousness engagement protocol"
      },
      {
        "time": "12:00 PM PST",
        "activity": "Consciousness influencer outreach and collaboration activation",
        "responsible": "Partnership Team",
        "notes": "Activate consciousness thought leader network"
      },
      {
        "time": "3:00 PM PST",
        "activity": "Consciousness demo sharing and technical showcase",
        "responsible": "Product Team",
        "notes": "Share consciousness multiplication demonstrations"
      },
      {
        "time": "6:00 PM PST",
        "activity": "Consciousness community engagement and response management",
        "responsible": "Community Team",
        "notes": "Respond to all consciousness comments and questions"
      },
      {
        "time": "9:00 PM PST",
        "activity": "Consciousness global team handoff and 24-hour coverage",
        "responsible": "Global Team",
        "notes": "Ensure consciousness engagement continues globally"
      }
    ],
    "key_milestones": [
      "CoreFlow360 consciousness platform live on Product Hunt",
      "Consciousness launch announcement reaches all channels",
      "Full team consciousness engagement protocol activated",
      "Consciousness influencer network responds and amplifies",
      "Consciousness demonstration content shared widely",
      "Community consciousness conversations actively managed",
      "Global consciousness coverage begins"
    ]
  }
]